pyfactor/VERSION
pyfactor/__init__.py
pyfactor/_cli.py
pyfactor/_graph.py
pyfactor/_gv.py
pyfactor/_io.py
pyfactor/_visit/__init__.py
pyfactor/_visit/base.py
pyfactor-0.4.1.dist-info/LICENSE
pyfactor-0.4.1.dist-info/METADATA
pyfactor-0.4.1.dist-info/WHEEL
pyfactor-0.4.1.dist-info/entry_points.txt
pyfactor-0.4.1.dist-info/top_level.txt
pyfactor-0.4.1.dist-info/RECORD
